edge_st_sdk/__init__.py
edge_st_sdk/edge_client.py
edge_st_sdk/aws/__init__.py
edge_st_sdk/aws/aws_client.py
edge_st_sdk/aws/aws_greengrass.py
edge_st_sdk/utils/__init__.py
edge_st_sdk/utils/edge_st_exceptions.py
edge_st_sdk/utils/python_utils.py
edge_st_sdk-1.3.4.dist-info/LICENSE
edge_st_sdk-1.3.4.dist-info/METADATA
edge_st_sdk-1.3.4.dist-info/WHEEL
edge_st_sdk-1.3.4.dist-info/top_level.txt
edge_st_sdk-1.3.4.dist-info/RECORD
