Metadata-Version: 2.1
Name: edge-st-sdk
Version: 1.3.4
Summary: IoT edge computing abstraction library package.
Home-page: https://github.com/STMicroelectronics/EdgeSTSDK_Python
Author: Davide Aliprandi
Author-email: davide.aliprandi@gmail.com
License: BSD 3-clause
Platform: UNKNOWN
Classifier: License :: OSI Approved :: BSD License
Classifier: Operating System :: POSIX :: Linux
Classifier: Programming Language :: Python :: 3.5
Classifier: Topic :: Software Development :: Embedded Systems
